{
  "parent": "woodcutter:recipes/root",
  "rewards": {
    "recipes": ["woodcutter:spruce_wood_woodcutting"]
  },
  "criteria": {
    "has_spruce_log": {
      "trigger": "minecraft:inventory_changed",
      "conditions": {
        "items": [
          {
            "items": ["minecraft:spruce_log"]
          }
        ]
      }
    },
    "has_the_recipe": {
      "trigger": "minecraft:recipe_unlocked",
      "conditions": {
        "recipe": "woodcutter:spruce_wood_woodcutting"
      }
    }
  },
  "requirements": [
    [
      "has_spruce_log",
      "has_the_recipe"
    ]
  ]
}